mokit_tui/__init__.py
mokit_tui/css.py
mokit_tui/gen.py
mokit_tui/main.py
mokit_tui/parser.py
mokit_tui/screens.py
mokit_tui/widgets.py
mokit_tui/workflow.py
mokit_tui-0.2.1.dist-info/METADATA
mokit_tui-0.2.1.dist-info/WHEEL
mokit_tui-0.2.1.dist-info/entry_points.txt
mokit_tui-0.2.1.dist-info/top_level.txt
mokit_tui-0.2.1.dist-info/RECORD
