Metadata-Version: 2.4
Name: mokit-tui
Version: 0.2.1
Summary: MOKIT TUI
Author: MOKIT TUI Developers
Maintainer: MOKIT TUI Developers
License-Expression: GPL-3.0-only
Classifier: Development Status :: 3 - Alpha
Classifier: Intended Audience :: Science/Research
Classifier: Programming Language :: Python :: 3
Classifier: Programming Language :: Python :: 3.8
Classifier: Programming Language :: Python :: 3.9
Classifier: Programming Language :: Python :: 3.10
Classifier: Programming Language :: Python :: 3.11
Classifier: Programming Language :: Python :: 3.12
Classifier: Topic :: Scientific/Engineering :: Chemistry
Requires-Python: >=3.8
Requires-Dist: textual
